sphinxcontrib/__init__.py
sphinxcontrib/traceables/__init__.py
sphinxcontrib/traceables/display.py
sphinxcontrib/traceables/filter.py
sphinxcontrib/traceables/graph.py
sphinxcontrib/traceables/infrastructure.py
sphinxcontrib/traceables/list.py
sphinxcontrib/traceables/matrix.py
sphinxcontrib/traceables/traceables.py
sphinxcontrib/traceables/utils.py
sphinxcontrib/traceables/static/traceables-matrix.css
tests/__init__.py
tests/conftest.py
tests/path.py
tests/test_basics.py
tests/test_builders.py
tests/test_errors.py
tests/test_filter.py
tests/test_graph.py
tests/test_infrastructure.py
tests/test_list.py
tests/test_matrix.py
tests/test_traceable_matrix.py
sphinxcontrib_traceables0.2-0.2.0.dist-info/LICENSE.rst
sphinxcontrib_traceables0.2-0.2.0.dist-info/METADATA
sphinxcontrib_traceables0.2-0.2.0.dist-info/WHEEL
sphinxcontrib_traceables0.2-0.2.0.dist-info/top_level.txt
sphinxcontrib_traceables0.2-0.2.0.dist-info/RECORD
