Metadata-Version: 2.1
Name: sphinxcontrib-traceables0.2
Version: 0.2.0
Summary: Sphinx extension that adds traceability within documentation
Home-page: https://github.com/superzerg/sphinxcontrib-traceables
Author: Yves Renier
Author-email: yves.renier@epfl.ch
License: Apache 2.0
Platform: any
Classifier: Development Status :: 3 - Alpha
Classifier: Environment :: Other Environment
Classifier: Environment :: Plugins
Classifier: Framework :: Sphinx :: Extension
Classifier: Intended Audience :: Developers
Classifier: Intended Audience :: Information Technology
Classifier: Intended Audience :: Science/Research
Classifier: Intended Audience :: System Administrators
Classifier: License :: OSI Approved :: Apache Software License
Classifier: Natural Language :: English
Classifier: Operating System :: OS Independent
Classifier: Programming Language :: Python :: 3
Classifier: Topic :: Software Development :: Documentation
Classifier: Topic :: Software Development :: Libraries :: Python Modules
Requires-Dist: Sphinx (>=2.1)
Requires-Dist: graphviz (>=0.4.6)
